Ios9RenjijiaohuZhinan/README.md
Ios9RenjijiaohuZhinan/__init__.py
Ios9RenjijiaohuZhinan/__main__.py
Ios9RenjijiaohuZhinan/file.epub
Ios9RenjijiaohuZhinan/index.html
Ios9RenjijiaohuZhinan/css/__init__.py
Ios9RenjijiaohuZhinan/css/annotations.css
Ios9RenjijiaohuZhinan/css/main.css
Ios9RenjijiaohuZhinan/css/normalize.css
Ios9RenjijiaohuZhinan/css/popup.css
Ios9RenjijiaohuZhinan/font/__init__.py
Ios9RenjijiaohuZhinan/font/fontello.eot
Ios9RenjijiaohuZhinan/font/fontello.svg
Ios9RenjijiaohuZhinan/font/fontello.ttf
Ios9RenjijiaohuZhinan/font/fontello.woff
Ios9RenjijiaohuZhinan/img/__init__.py
Ios9RenjijiaohuZhinan/img/annotator-glyph-sprite.png
Ios9RenjijiaohuZhinan/img/annotator-icon-sprite.png
Ios9RenjijiaohuZhinan/img/apple-touch-icon.png
Ios9RenjijiaohuZhinan/img/cancelfullscreen.png
Ios9RenjijiaohuZhinan/img/close.png
Ios9RenjijiaohuZhinan/img/fullscreen.png
Ios9RenjijiaohuZhinan/img/loader.gif
Ios9RenjijiaohuZhinan/img/menu-icon.png
Ios9RenjijiaohuZhinan/img/save.png
Ios9RenjijiaohuZhinan/img/saved.png
Ios9RenjijiaohuZhinan/img/settings-s.png
Ios9RenjijiaohuZhinan/img/settings.png
Ios9RenjijiaohuZhinan/img/star.png
Ios9RenjijiaohuZhinan/js/__init__.py
Ios9RenjijiaohuZhinan/js/epub.js
Ios9RenjijiaohuZhinan/js/epub.min.js
Ios9RenjijiaohuZhinan/js/epub.min.map
Ios9RenjijiaohuZhinan/js/hooks.min.js
Ios9RenjijiaohuZhinan/js/hooks.min.map
Ios9RenjijiaohuZhinan/js/reader.js
Ios9RenjijiaohuZhinan/js/reader.js.map
Ios9RenjijiaohuZhinan/js/reader.min.js
Ios9RenjijiaohuZhinan/js/reader.min.map
Ios9RenjijiaohuZhinan/js/hooks/__init__.py
Ios9RenjijiaohuZhinan/js/hooks/extensions/__init__.py
Ios9RenjijiaohuZhinan/js/hooks/extensions/highlight.js
Ios9RenjijiaohuZhinan/js/libs/__init__.py
Ios9RenjijiaohuZhinan/js/libs/jquery.min.js
Ios9RenjijiaohuZhinan/js/libs/localforage.min.js
Ios9RenjijiaohuZhinan/js/libs/screenfull.js
Ios9RenjijiaohuZhinan/js/libs/screenfull.min.js
Ios9RenjijiaohuZhinan/js/libs/zip.min.js
Ios9RenjijiaohuZhinan/js/plugins/__init__.py
ios_9_renjijiaohu_zhinan-2024.3.4.0.dist-info/METADATA
ios_9_renjijiaohu_zhinan-2024.3.4.0.dist-info/WHEEL
ios_9_renjijiaohu_zhinan-2024.3.4.0.dist-info/entry_points.txt
ios_9_renjijiaohu_zhinan-2024.3.4.0.dist-info/top_level.txt
ios_9_renjijiaohu_zhinan-2024.3.4.0.dist-info/RECORD
